gforms/__init__.py
gforms/elements.py
gforms/elements_base.py
gforms/errors.py
gforms/form.py
gforms/media.py
gforms/options.py
gforms/util.py
gforms/validators.py
gforms-1.3.2.dist-info/LICENSE
gforms-1.3.2.dist-info/METADATA
gforms-1.3.2.dist-info/WHEEL
gforms-1.3.2.dist-info/top_level.txt
gforms-1.3.2.dist-info/RECORD
